{"src/lambda_handler.py": [{"type": "function", "rank": "A", "endline": 27, "complexity": 2, "name": "handler", "col_offset": 0, "lineno": 5, "closures": []}], "src/todolist.py": [{"type": "method", "rank": "A", "endline": 57, "complexity": 3, "name": "_create_table", "col_offset": 4, "lineno": 20, "classname": "App", "closures": []}, {"type": "method", "rank": "A", "endline": 193, "complexity": 3, "name": "update", "col_offset": 4, "lineno": 166, "classname": "App", "closures": []}, {"type": "class", "rank": "A", "endline": 193, "complexity": 2, "name": "App", "col_offset": 0, "lineno": 10, "methods": [{"type": "method", "rank": "A", "endline": 18, "complexity": 2, "name": "__init__", "col_offset": 4, "lineno": 11, "classname": "App", "closures": []}, {"type": "method", "rank": "A", "endline": 57, "complexity": 3, "name": "_create_table", "col_offset": 4, "lineno": 20, "classname": "App", "closures": []}, {"type": "method", "rank": "A", "endline": 64, "complexity": 1, "name": "try_me", "col_offset": 4, "lineno": 59, "classname": "App", "closures": []}, {"type": "method", "rank": "A", "endline": 88, "complexity": 2, "name": "create", "col_offset": 4, "lineno": 66, "classname": "App", "closures": []}, {"type": "method", "rank": "A", "endline": 104, "complexity": 1, "name": "delete", "col_offset": 4, "lineno": 90, "classname": "App", "closures": []}, {"type": "method", "rank": "A", "endline": 120, "complexity": 1, "name": "get", "col_offset": 4, "lineno": 106, "classname": "App", "closures": []}, {"type": "method", "rank": "A", "endline": 130, "complexity": 1, "name": "show", "col_offset": 4, "lineno": 122, "classname": "App", "closures": []}, {"type": "method", "rank": "A", "endline": 164, "complexity": 2, "name": "translate", "col_offset": 4, "lineno": 132, "classname": "App", "closures": []}, {"type": "method", "rank": "A", "endline": 193, "complexity": 3, "name": "update", "col_offset": 4, "lineno": 166, "classname": "App", "closures": []}]}, {"type": "method", "rank": "A", "endline": 18, "complexity": 2, "name": "__init__", "col_offset": 4, "lineno": 11, "classname": "App", "closures": []}, {"type": "method", "rank": "A", "endline": 88, "complexity": 2, "name": "create", "col_offset": 4, "lineno": 66, "classname": "App", "closures": []}, {"type": "method", "rank": "A", "endline": 164, "complexity": 2, "name": "translate", "col_offset": 4, "lineno": 132, "classname": "App", "closures": []}, {"type": "method", "rank": "A", "endline": 64, "complexity": 1, "name": "try_me", "col_offset": 4, "lineno": 59, "classname": "App", "closures": []}, {"type": "method", "rank": "A", "endline": 104, "complexity": 1, "name": "delete", "col_offset": 4, "lineno": 90, "classname": "App", "closures": []}, {"type": "method", "rank": "A", "endline": 120, "complexity": 1, "name": "get", "col_offset": 4, "lineno": 106, "classname": "App", "closures": []}, {"type": "method", "rank": "A", "endline": 130, "complexity": 1, "name": "show", "col_offset": 4, "lineno": 122, "classname": "App", "closures": []}], "src/decimalencoder.py": [{"type": "class", "rank": "A", "endline": 10, "complexity": 3, "name": "DecimalEncoder", "col_offset": 0, "lineno": 6, "methods": [{"type": "method", "rank": "A", "endline": 10, "complexity": 2, "name": "default", "col_offset": 4, "lineno": 7, "classname": "DecimalEncoder", "closures": []}]}, {"type": "method", "rank": "A", "endline": 10, "complexity": 2, "name": "default", "col_offset": 4, "lineno": 7, "classname": "DecimalEncoder", "closures": []}]}
